agentocr/__init__.py
agentocr/infer/__init__.py
agentocr/infer/cls.py
agentocr/infer/det.py
agentocr/infer/rec.py
agentocr/infer/server.py
agentocr/infer/system.py
agentocr/infer/utility.py
agentocr/postprocess/__init__.py
agentocr/postprocess/cls_postprocess.py
agentocr/postprocess/db_postprocess.py
agentocr/postprocess/east_postprocess.py
agentocr/postprocess/locality_aware_nms.py
agentocr/postprocess/rec_postprocess.py
agentocr/postprocess/sast_postprocess.py
agentocr/preprocess/__init__.py
agentocr/preprocess/label_ops.py
agentocr/preprocess/operators.py
agentocr/resources/char_dicts/ar_dict.txt
agentocr/resources/char_dicts/ch_dict.txt
agentocr/resources/char_dicts/cht_dict.txt
agentocr/resources/char_dicts/cy_dict.txt
agentocr/resources/char_dicts/de_dict.txt
agentocr/resources/char_dicts/en_dict.txt
agentocr/resources/char_dicts/fr_dict.txt
agentocr/resources/char_dicts/ger_dict.txt
agentocr/resources/char_dicts/jp_dict.txt
agentocr/resources/char_dicts/ka_dict.txt
agentocr/resources/char_dicts/kr_dict.txt
agentocr/resources/char_dicts/la_dict.txt
agentocr/resources/char_dicts/ta_dict.txt
agentocr/resources/char_dicts/te_dict.txt
agentocr-2.0.0.dist-info/LICENSE
agentocr-2.0.0.dist-info/METADATA
agentocr-2.0.0.dist-info/WHEEL
agentocr-2.0.0.dist-info/entry_points.txt
agentocr-2.0.0.dist-info/top_level.txt
agentocr-2.0.0.dist-info/RECORD
