Metadata-Version: 2.1
Name: agentocr
Version: 2.0.0
Summary: An easy-to-use OCR package with multilingual support.
Home-page: https://github.com/AgentMaker/AgentOCR
Author: jm12138
License: Apache License 2.0
Platform: UNKNOWN
License-File: LICENSE
Requires-Dist: six
Requires-Dist: wget
Requires-Dist: numpy
Requires-Dist: flask
Requires-Dist: gevent
Requires-Dist: pillow
Requires-Dist: shapely
Requires-Dist: pyclipper
Requires-Dist: opencv-python
